odoo/addons/hr_org_chart_overview/README.rst
odoo/addons/hr_org_chart_overview/__init__.py
odoo/addons/hr_org_chart_overview/__manifest__.py
odoo/addons/hr_org_chart_overview/i18n/hr_org_chart_overview.pot
odoo/addons/hr_org_chart_overview/i18n/it.po
odoo/addons/hr_org_chart_overview/i18n/pt_BR.po
odoo/addons/hr_org_chart_overview/i18n/sv.po
odoo/addons/hr_org_chart_overview/models/__init__.py
odoo/addons/hr_org_chart_overview/models/hr_employee.py
odoo/addons/hr_org_chart_overview/readme/CONTRIBUTORS.rst
odoo/addons/hr_org_chart_overview/readme/DESCRIPTION.rst
odoo/addons/hr_org_chart_overview/readme/USAGE.rst
odoo/addons/hr_org_chart_overview/static/description/icon.png
odoo/addons/hr_org_chart_overview/static/description/index.html
odoo/addons/hr_org_chart_overview/static/src/js/hr_org_chart_overview.js
odoo/addons/hr_org_chart_overview/static/src/lib/orgchart/html2canvas.min.js
odoo/addons/hr_org_chart_overview/static/src/lib/orgchart/jquery.orgchart.css
odoo/addons/hr_org_chart_overview/static/src/lib/orgchart/jquery.orgchart.js
odoo/addons/hr_org_chart_overview/static/src/lib/orgchart/jspdf.min.js
odoo/addons/hr_org_chart_overview/static/src/scss/hr_org_chart_style.scss
odoo/addons/hr_org_chart_overview/static/src/xml/hr_org_chart_overview.xml
odoo/addons/hr_org_chart_overview/views/hr_views.xml
odoo_addon_hr_org_chart_overview-16.0.1.0.0.2.dist-info/METADATA
odoo_addon_hr_org_chart_overview-16.0.1.0.0.2.dist-info/WHEEL
odoo_addon_hr_org_chart_overview-16.0.1.0.0.2.dist-info/top_level.txt
odoo_addon_hr_org_chart_overview-16.0.1.0.0.2.dist-info/RECORD
